tokenish/__init__.py
tokenish/tokenish.py
tokenish/lib/__init__.py
tokenish/lib/encoder.py
tokenish/lib/result_writer.py
tokenish/lib/tokenizer.py
tokenish-0.1.data/scripts/tokenish
tokenish-0.1.dist-info/LICENSE
tokenish-0.1.dist-info/METADATA
tokenish-0.1.dist-info/WHEEL
tokenish-0.1.dist-info/top_level.txt
tokenish-0.1.dist-info/RECORD
