Metadata-Version: 2.1
Name: tokenish
Version: 0.1
Summary: A simple tool to fill pattern with tokens from file or directory.
Home-page: https://github.com/VictorMeyer77/tokenish
Author: Victor Meyer
Author-email: victor_meyer@outlook.fr
License: MIT
Project-URL: Bug Tracker, https://github.com/VictorMeyer77/tokenish/issues
Project-URL: Changelog, https://github.com/VictorMeyer77/tokenish/blob/main/CHANGELOG.md
Project-URL: Documentation, https://github.com/VictorMeyer77/tokenish/blob/main/README.md
Project-URL: Source, https://github.com/VictorMeyer77/tokenish
Keywords: token encode pattern sh
Platform: any
Classifier: Development Status :: 4 - Beta
Classifier: Environment :: Console
Classifier: Intended Audience :: Developers
Classifier: Intended Audience :: System Administrators
Classifier: License :: OSI Approved :: MIT License
Classifier: Operating System :: MacOS :: MacOS X
Classifier: Operating System :: POSIX
Classifier: Programming Language :: Python
Requires-Python: <4,>=3.6
License-File: LICENSE
